loop/__init__.py
loop/concurrency.py
loop/core.py
loop/functional.py
loop/packing.py
loop/progress.py
loop_python-0.4.0.dist-info/METADATA
loop_python-0.4.0.dist-info/WHEEL
loop_python-0.4.0.dist-info/top_level.txt
loop_python-0.4.0.dist-info/RECORD
