Metadata-Version: 2.1
Name: loop-python
Version: 0.4.0
Summary: Replace common looping boilerplate with pretty method chaining.
Author-email: Artium Dashuta <artium89@gmail.com>
License: MIT License
Project-URL: Repository, https://github.com/artiumd/loop
Project-URL: Documentation, https://artiumd.github.io/loop
Classifier: Programming Language :: Python :: 3
Classifier: License :: OSI Approved :: MIT License
Classifier: Operating System :: OS Independent
Requires-Python: >=3.8
Requires-Dist: tqdm
Requires-Dist: types-tqdm
Requires-Dist: pathos
Requires-Dist: typing-extensions ; python_version < "3.11"
Provides-Extra: docs
Requires-Dist: mkdocs ==1.5.3 ; extra == 'docs'
Requires-Dist: mkdocs-material ==9.5.7 ; extra == 'docs'
Requires-Dist: mike ==2.0.0 ; extra == 'docs'
Requires-Dist: mkdocstrings[python] ==0.24.0 ; extra == 'docs'
Provides-Extra: tests
Requires-Dist: pytest ==7.4.4 ; extra == 'tests'
Requires-Dist: mypy ==1.8.0 ; extra == 'tests'
